yourlastfriend/__init__.py
yourlastfriend/hello.py
yourlastfriend-1.0.dist-info/METADATA
yourlastfriend-1.0.dist-info/WHEEL
yourlastfriend-1.0.dist-info/top_level.txt
yourlastfriend-1.0.dist-info/RECORD
