Metadata-Version: 2.1
Name: yourlastfriend
Version: 1.0
Summary: Dummy security test
Author: Rc)
Author-email: <rc@hustli.ng>
Keywords: python,video,stream,video stream,camera stream,sockets
Classifier: Development Status :: 1 - Planning
Classifier: Intended Audience :: Developers
Classifier: Programming Language :: Python :: 3
Classifier: Operating System :: Unix
Classifier: Operating System :: MacOS :: MacOS X
Classifier: Operating System :: Microsoft :: Windows
Requires-Dist: requests
